eventimpact/__init__.py
eventimpact/analyzer.py
eventimpact/plot.py
eventimpact-0.1.0.dist-info/licenses/LICENSE
eventimpact-0.1.0.dist-info/METADATA
eventimpact-0.1.0.dist-info/WHEEL
eventimpact-0.1.0.dist-info/top_level.txt
eventimpact-0.1.0.dist-info/RECORD
