Metadata-Version: 2.4
Name: eventimpact
Version: 0.1.0
Summary: Bayesian impact analysis for bounded events on time-series metrics.
Author-email: Tom Muga <tonmuga@gmail.com>
License-Expression: MIT
Keywords: bayesian,promotion,impact,time-series,analytics
Classifier: Programming Language :: Python :: 3
Classifier: Operating System :: OS Independent
Requires-Python: >=3.7
License-File: LICENSE
Requires-Dist: numpy>=1.26.4
Requires-Dist: scipy>=1.11.4
Requires-Dist: matplotlib>=3.6.3
Dynamic: license-file
